nbxmpp/__init__.py
nbxmpp/addresses.py
nbxmpp/client.py
nbxmpp/connection.py
nbxmpp/const.py
nbxmpp/dispatcher.py
nbxmpp/errors.py
nbxmpp/exceptions.py
nbxmpp/language.py
nbxmpp/namespaces.py
nbxmpp/old_dispatcher.py
nbxmpp/plugin.py
nbxmpp/precis.py
nbxmpp/protocol.py
nbxmpp/py.typed
nbxmpp/sasl.py
nbxmpp/simplexml.py
nbxmpp/smacks.py
nbxmpp/stringprep.py
nbxmpp/structs.py
nbxmpp/task.py
nbxmpp/tcp.py
nbxmpp/types.py
nbxmpp/util.py
nbxmpp/websocket.py
nbxmpp/xmppiri.py
nbxmpp/modules/__init__.py
nbxmpp/modules/activity.py
nbxmpp/modules/adhoc.py
nbxmpp/modules/annotations.py
nbxmpp/modules/attention.py
nbxmpp/modules/base.py
nbxmpp/modules/bits_of_binary.py
nbxmpp/modules/blocking.py
nbxmpp/modules/captcha.py
nbxmpp/modules/chat_markers.py
nbxmpp/modules/chatstates.py
nbxmpp/modules/correction.py
nbxmpp/modules/dataforms.py
nbxmpp/modules/date_and_time.py
nbxmpp/modules/delay.py
nbxmpp/modules/delimiter.py
nbxmpp/modules/discovery.py
nbxmpp/modules/eme.py
nbxmpp/modules/entity_caps.py
nbxmpp/modules/entity_time.py
nbxmpp/modules/fallback.py
nbxmpp/modules/http_auth.py
nbxmpp/modules/http_upload.py
nbxmpp/modules/ibb.py
nbxmpp/modules/idle.py
nbxmpp/modules/iq.py
nbxmpp/modules/last_activity.py
nbxmpp/modules/location.py
nbxmpp/modules/mam.py
nbxmpp/modules/mds.py
nbxmpp/modules/message.py
nbxmpp/modules/misc.py
nbxmpp/modules/mood.py
nbxmpp/modules/muclumbus.py
nbxmpp/modules/nickname.py
nbxmpp/modules/ogp.py
nbxmpp/modules/omemo.py
nbxmpp/modules/oob.py
nbxmpp/modules/openpgp.py
nbxmpp/modules/pgplegacy.py
nbxmpp/modules/ping.py
nbxmpp/modules/presence.py
nbxmpp/modules/pubsub.py
nbxmpp/modules/reactions.py
nbxmpp/modules/receipts.py
nbxmpp/modules/replies.py
nbxmpp/modules/retraction.py
nbxmpp/modules/roster.py
nbxmpp/modules/rsm.py
nbxmpp/modules/security_labels.py
nbxmpp/modules/software_version.py
nbxmpp/modules/tune.py
nbxmpp/modules/user_avatar.py
nbxmpp/modules/util.py
nbxmpp/modules/vcard4.py
nbxmpp/modules/vcard_avatar.py
nbxmpp/modules/vcard_temp.py
nbxmpp-7.0.0.dist-info/licenses/COPYING
nbxmpp-7.0.0.dist-info/METADATA
nbxmpp-7.0.0.dist-info/WHEEL
nbxmpp-7.0.0.dist-info/top_level.txt
nbxmpp-7.0.0.dist-info/RECORD
