Metadata-Version: 2.4
Name: nbxmpp
Version: 7.0.0
Summary: XMPP Library
Author-email: Philipp Hörist <philipp@hoerist.com>, Yann Leboulanger <yann@leboulanger.org>
License: GPL-3.0-or-later
Project-URL: repository, https://dev.gajim.org/gajim/python-nbxmpp
Keywords: chat,messaging,im,xmpp
Classifier: Programming Language :: Python :: 3.10
Requires-Python: >=3.10
License-File: COPYING
Requires-Dist: precis-i18n>=1.0.0
Requires-Dist: packaging
Requires-Dist: idna
Requires-Dist: PyGObject>=3.42.0
Provides-Extra: gssapi
Requires-Dist: gssapi; extra == "gssapi"
Provides-Extra: dev
Requires-Dist: black==24.10.0; extra == "dev"
Requires-Dist: isort>=5.13.2; extra == "dev"
Requires-Dist: ruff>=0.9.7; extra == "dev"
Dynamic: license-file
